Metadata-Version: 2.1
Name: siconfipy
Version: 0.0.3b1
Summary: Access data from the Brazilian Public Sector (SICONFI)
Home-page: https://github.com/pedrocastroo/siconfipy
Author: Pedro Castro
Author-email: pdesacastro@gmail.com
Maintainer: Pedro Castro
License: MIT
Platform: UNKNOWN
Classifier: Programming Language :: Python :: 3
Classifier: License :: OSI Approved :: MIT License
Classifier: Development Status :: 4 - Beta
Classifier: Topic :: Database
Requires-Python: >=3.6
